[{
  "_id": {
    "$oid": "671000000000000000000621"
  },
  "slot_name": "Tiết 1",
  "start_time": "08:30",
  "end_time": "09:00",
  "school_id": {
    "$oid": "671000000000000000000001"
  },
  "createdAt": {
    "$date": "2025-10-29T16:16:08.792Z"
  },
  "updatedAt": {
    "$date": "2025-11-26T18:29:08.931Z"
  }
},
{
  "_id": {
    "$oid": "671000000000000000000622"
  },
  "slot_name": "Tiết 2",
  "start_time": "09:15",
  "end_time": "10:00",
  "school_id": {
    "$oid": "671000000000000000000001"
  },
  "createdAt": {
    "$date": "2025-10-29T16:16:08.792Z"
  },
  "updatedAt": {
    "$date": "2025-11-26T18:29:08.943Z"
  }
},
{
  "_id": {
    "$oid": "6922ee45a48de2bf38c944f8"
  },
  "slot_name": "Nghỉ trưa",
  "start_time": "10:25",
  "end_time": "11:26",
  "school_id": {
    "$oid": "671000000000000000000001"
  },
  "createdAt": {
    "$date": "2025-11-23T11:21:41.846Z"
  },
  "updatedAt": {
    "$date": "2025-11-26T18:30:33.004Z"
  },
  "__v": 0
}]
